sine_generator/__init__.py
sine_generator/main.py
sine_generator-0.1.0.dist-info/METADATA
sine_generator-0.1.0.dist-info/WHEEL
sine_generator-0.1.0.dist-info/top_level.txt
sine_generator-0.1.0.dist-info/RECORD
