Metadata-Version: 2.1
Name: sine_generator
Version: 0.1.0
Summary: A library to generate sinusoidal waveforms with a DC offset.
Author: K ABHISHEK MENON
Author-email: kabhishekmenon@gmail.com
Classifier: Programming Language :: Python :: 3
Classifier: License :: OSI Approved :: MIT License
Classifier: Operating System :: OS Independent
Requires-Python: >=3.6
Requires-Dist: numpy
Provides-Extra: dev
Requires-Dist: matplotlib ; extra == 'dev'
Requires-Dist: unittest ; extra == 'dev'
